ejercicio 3/demux/src/demux1to4_behavioral.v
module demux1to4(out,sel,data,enable);

    input           enable, data;
    input[1:0]      sel;
    output reg[3:0] out;
    integer         k;

    always @(sel, data, enable)
        for(k = 0; k < 4; k = k + 1)
            if((sel == k)&&(enable == 1))
                out[k] = data;
            else
                out[k] = 0;
endmodule

ejercicio 3/demux/src/demux_tb.v
`include "src/demux1to4.v"

module demux_tb;

    reg[1:0]    sel;
    reg         data, enable;
    wire[3:0]   out;

    demux1to4 dut(out, sel, data, enable);

    integer k;

    initial begin
        $dumpfile("demux1to4.vcd");
        $dumpvars(0, demux_tb);

        enable = 0; data = 0; sel = 0; #10;
        enable = 0; data = 0; sel = 1; #10;
        enable = 0; data = 0; sel = 2; #10;
        enable = 0; data = 0; sel = 3; #10;

        enable = 0; data = 1; sel = 0; #10;
        enable = 0; data = 1; sel = 1; #10;
        enable = 0; data = 1; sel = 2; #10;
        enable = 0; data = 1; sel = 3; #10;

        enable = 1; data = 0; sel = 0; #10;
        enable = 1; data = 0; sel = 1; #10;
        enable = 1; data = 0; sel = 2; #10;
        enable = 1; data = 0; sel = 3; #10;

        enable = 1; data = 1; sel = 0; #10;
        enable = 1; data = 1; sel = 1; #10;
        enable = 1; data = 1; sel = 2; #10;
        enable = 1; data = 1; sel = 3; #10;

        $finish;
    end

    initial
        $monitor("At time %2t:\n\tenable = %b - data = %b - sel = %b - out = %b",
                 $time, enable, data, sel, out);

endmodule

ejercicio 3/demux/demux1to4.vcd
$date
	Tue Aug 21 17:08:55 2018
$end
$version
	Icarus Verilog
$end
$timescale
	1s
$end
$scope module demux_tb $end
$var wire 4 ! out [3:0] $end
$var reg 1 " data $end
$var reg 1 # enable $end
$var reg 2 $ sel [1:0] $end
$scope module dut $end
$var wire 1 " data $end
$var wire 1 # enable $end
$var wire 2 % sel [1:0] $end
$var reg 4 & out [3:0] $end
$var integer 32 ' k [31:0] $end
$upscope $end
$upscope $end
$enddefinitions $end
#0
$dumpvars
b100 '
b0 &
b0 %
b0 $
0#
0"
b0 !
$end
#10
b100 '
b1 $
b1 %
#20
b100 '
b10 $
b10 %
#30
b100 '
b11 $
b11 %
#40
b100 '
b0 $
b0 %
1"
#50
b100 '
b1 $
b1 %
#60
b100 '
b10 $
b10 %
#70
b100 '
b11 $
b11 %
#80
b100 '
b0 $
b0 %
0"
1#
#90
b100 '
b1 $
b1 %
#100
b100 '
b10 $
b10 %
#110
b100 '
b11 $
b11 %
#120
b1 !
b1 &
b100 '
b0 $
b0 %
1"
#130
b10 !
b10 &
b100 '
b1 $
b1 %
#140
b100 !
b100 &
b100 '
b10 $
b10 %
#150
b1000 !
b1000 &
b100 '
b11 $
b11 %
